analytics/__init__.py
analytics/turnout_tier_categorization.py
tests/__init__.py
tests/test_turnout_tier_categorization.py
turnout_tier_categorization-0.2.0.dist-info/LICENSE.txt
turnout_tier_categorization-0.2.0.dist-info/METADATA
turnout_tier_categorization-0.2.0.dist-info/WHEEL
turnout_tier_categorization-0.2.0.dist-info/top_level.txt
turnout_tier_categorization-0.2.0.dist-info/RECORD
