Metadata-Version: 2.1
Name: turnout_tier_categorization
Version: 0.2.0
Summary: A function to add a turnout tier categorization column to a pandas DataFrame
Home-page: https://github.com/davidwhite/turnout_tier_categorization
Author: David White
Author-email: david@generationdata.org
Classifier: Programming Language :: Python :: 3
Classifier: License :: OSI Approved :: MIT License
Classifier: Operating System :: OS Independent
Requires-Python: >=3.6
License-File: LICENSE.txt
Requires-Dist: pandas >=1.0
